brickalize/__init__.py
brickalize/bricks.py
brickalize/converter.py
brickalize/model.py
brickalize/visualizer.py
brickalize-1.0.1.dist-info/licenses/LICENSE
brickalize-1.0.1.dist-info/METADATA
brickalize-1.0.1.dist-info/WHEEL
brickalize-1.0.1.dist-info/top_level.txt
brickalize-1.0.1.dist-info/RECORD
