Metadata-Version: 2.4
Name: brickalize
Version: 1.0.1
Summary: A package for converting 3D models to LEGO-like brick structures and visualizing them.
Author-email: "Sten Nellen (Creative Mindstorms)" <creativemindstorms1@gmail.com>
License:                     GNU GENERAL PUBLIC LICENSE
Project-URL: Homepage, https://github.com/CreativeMindstorms/brickalize
Project-URL: Documentation, https://brickalize.readthedocs.io/en/latest/
Keywords: 3D,LEGO,modeling
Classifier: Programming Language :: Python :: 3
Classifier: License :: OSI Approved :: GNU General Public License v3 (GPLv3)
Classifier: Operating System :: OS Independent
Classifier: Topic :: Scientific/Engineering :: Visualization
Classifier: Topic :: Multimedia :: Graphics :: 3D Modeling
Requires-Python: >=3.8
License-File: LICENSE
Requires-Dist: numpy
Requires-Dist: open3d
Requires-Dist: trimesh
Requires-Dist: tqdm
Requires-Dist: opencv-python
Requires-Dist: scipy
Requires-Dist: rtree
Dynamic: license-file
